discord_webhook/__init__.py
discord_webhook/__main__.py
discord_webhook/async_webhook.py
discord_webhook/py.typed
discord_webhook/webhook.py
discord_webhook/webhook_exceptions.py
python_discord_webhook-1.0.0.dist-info/entry_points.txt
python_discord_webhook-1.0.0.dist-info/LICENSE
python_discord_webhook-1.0.0.dist-info/WHEEL
python_discord_webhook-1.0.0.dist-info/METADATA
python_discord_webhook-1.0.0.dist-info/RECORD
