Metadata-Version: 2.1
Name: python-discord-webhook
Version: 1.0.0
Summary: execute discord webhooks
Home-page: https://github.com/lovvskillz/python-discord-webhook
License: MIT
Keywords: discord,webhook
Author: lovvskillz
Author-email: 14542790+lovvskillz@users.noreply.github.com
Requires-Python: >=3.8,<4.0
Classifier: License :: OSI Approved :: MIT License
Classifier: Programming Language :: Python :: 3
Classifier: Programming Language :: Python :: 3.8
Classifier: Programming Language :: Python :: 3.9
Classifier: Programming Language :: Python :: 3.10
Provides-Extra: async
Requires-Dist: httpx (>=0.23.0,<0.24.0); extra == "async"
Requires-Dist: requests (>=2.28.1,<3.0.0)
Project-URL: Repository, https://github.com/lovvskillz/python-discord-webhook
